Metadata-Version: 1.0
Name: joshy-distributions
Version: 0.1
Summary: Gaussian distributions
Home-page: UNKNOWN
Author: Joshua Adewolu
Author-email: ija236@nyu.edu
License: UNKNOWN
Platform: UNKNOWN
